cog/__init__.py
cog/cache.py
cog/config.py
cog/core.py
cog/database.py
cog/torque.py
cog/view.py
cogdb-3.4.4.dist-info/licenses/LICENSE
cogdb-3.4.4.dist-info/METADATA
cogdb-3.4.4.dist-info/WHEEL
cogdb-3.4.4.dist-info/top_level.txt
cogdb-3.4.4.dist-info/RECORD
